saeonobspy/__init__.py
saeonobspy/_version.py
saeonobspy/api.py
tests/__init__.py
tests/test_api.py
saeonobspy-0.2.0.dist-info/LICENSE
saeonobspy-0.2.0.dist-info/METADATA
saeonobspy-0.2.0.dist-info/WHEEL
saeonobspy-0.2.0.dist-info/top_level.txt
saeonobspy-0.2.0.dist-info/RECORD
