Metadata-Version: 2.1
Name: saeonobspy
Version: 0.2.0
Summary: Python package to interact with the SAEON Observation Database API
Home-page: https://github.com/GMoncrieff/saeonobspy
Author: Glenn Moncrieff
Author-email: glenn@saeon.ac.za
License: MIT
Platform: UNKNOWN
Classifier: License :: OSI Approved :: MIT License
Classifier: Programming Language :: Python :: 3
Classifier: Operating System :: OS Independent
Requires-Python: >=3.8
License-File: LICENSE
Requires-Dist: pandas
Requires-Dist: geopandas
Requires-Dist: requests
Requires-Dist: shapely
Requires-Dist: aiohttp
